"test_abc_saaketh/__init__,py"
test_abc_saaketh/a.py
test_abc_saaketh/b.py
test_abc_saaketh/c.py
test_abc_saaketh-0.0.1.dist-info/LICENSE
test_abc_saaketh-0.0.1.dist-info/METADATA
test_abc_saaketh-0.0.1.dist-info/WHEEL
test_abc_saaketh-0.0.1.dist-info/RECORD
